{
  "$schema": "https://developer.microsoft.com/json-schemas/spfx/client-side-web-part-manifest.schema.json",
  "id": "4c383c96-1d07-4f0d-b46b-9fc7968df23f",
  "alias": "Drilldown7WebPart",
  "componentType": "WebPart",

  // The "*" signifies that the version should be taken from the package.json
  "version": "*",
  "manifestVersion": 2,

  // If true, the component can only be installed on sites where Custom Script is allowed.
  // Components that allow authors to embed arbitrary script code should set this to true.
  // https://support.office.com/en-us/article/Turn-scripting-capabilities-on-or-off-1f2c515f-5d7e-448a-9fd7-835da935584f
  "requiresCustomScript": false,
  "supportedHosts": ["SharePointWebPart"],

  "preconfiguredEntries": [{
    "groupId": "5c03119e-3074-46fd-976b-c60198311f70", // Other
    "group": { "default": "Other" },
    "title": { "default": "Drilldown7" },
    "description": { "default": "Drilldown7 cascading filters" },
    "officeFabricIconFontName": "DrillExpand",
    "properties": {
      "description": "Drilldown7",
      "parentListTitle": "TrackMyTime",
      "webPartScenario": "TEAM",
      "refiner0": "Story",
      "refiner1": "Chapter",
      "refiner2": "Created",
      "rules0def": "",
      "rules1def": "",
      "rules2def": "groupByMonthsMMM",
      "viewWidth1": 1000,
      "viewWidth2": 700,
      "viewWidth3": 400,
      "listDefinition": "",
      "includeDetails": true,

      "showCatCounts": false,
      "showSummary": false,
      
      "groupByFields": "",
      "togCounts": false,
      "togSummary": true,
      "togStats": true,
      "fetchCount": 200,
      "fetchCountMobile": 200,
      "restFilter": "",

      "viewJSON1": "[{ \"name\": \"Id\", \"displayName\": \"Id\", \"minWidth\": 50 },{ \"name\": \"Title\", \"displayName\": \"Title\", \"minWidth\": 200 },{ \"name\": \"Created\", \"displayName\": \"Created\", \"minWidth\": 200 },{ \"name\": \"Modified\", \"displayName\": \"Modified\", \"minWidth\": 200 }]",
      "viewJSON2": "[{ \"name\": \"Id\", \"displayName\": \"Id\", \"minWidth\": 50 },{ \"name\": \"Title\", \"displayName\": \"Title\", \"minWidth\": 200 },{ \"name\": \"Modified\", \"displayName\": \"Modified\", \"minWidth\": 200 }]",
      "viewJSON3": "[{ \"name\": \"Id\", \"displayName\": \"Id\", \"minWidth\": 50 },{ \"name\": \"Title\", \"displayName\": \"Title\", \"minWidth\": 200 }]",
      
      "stats": "[{ \"primaryField\": \"Created\", \"secondField\": \"currentTime\", \"title\": \"Created Age\", \"stat\": \"avg\", \"chartTypes\": [\"pareto-dec\"],\"ignore\": [{\"field\": \"EntryType\",\"op\" : \"eq\",\"val\" : \"start\"}] },{ \"primaryField\": \"Modified\", \"secondField\": \"currentTime\", \"title\": \"Modified Age\", \"stat\": \"sum\", \"chartTypes\": [\"pareto-dec\"],\"ignore\": [{\"field\": \"EntryType\",\"op\" : \"eq\",\"val\" : \"start\"}] }]"
    }
  }]
}
